physiofit/__init__.py
physiofit/__main__.py
physiofit/base/__init__.py
physiofit/base/fitter.py
physiofit/base/io.py
physiofit/example_yaml.yml
physiofit/models/__init__.py
physiofit/models/base_model.py
physiofit/models/model_1.py
physiofit/models/model_2.py
physiofit/models/model_3.py
physiofit/models/model_4.py
physiofit/models/model_5.py
physiofit/tests/__init__.py
physiofit/tests/conftest.py
physiofit/tests/test_base.py
physiofit/ui/__init__.py
physiofit/ui/cli.py
physiofit/ui/gui.py
physiofit-3.3.6.dist-info/entry_points.txt
physiofit-3.3.6.dist-info/METADATA
physiofit-3.3.6.dist-info/WHEEL
physiofit-3.3.6.dist-info/LICENSE
physiofit-3.3.6.dist-info/RECORD
