Metadata-Version: 2.1
Name: physiofit
Version: 3.3.6
Summary: Calculate extracellular fluxes from metabolite concentrations and biomass data
License: GNU General Public License (GPL)
Author: llegregam
Author-email: legregam@insa-toulouse.fr
Requires-Python: >=3.8, !=2.7.*, !=3.0.*, !=3.1.*, !=3.2.*, !=3.3.*, !=3.4.*, !=3.5.*, !=3.6.*, !=3.7.*
Classifier: License :: Other/Proprietary License
Classifier: Programming Language :: Python :: 3
Classifier: Programming Language :: Python :: 3.8
Classifier: Programming Language :: Python :: 3.9
Classifier: Programming Language :: Python :: 3.10
Classifier: Programming Language :: Python :: 3.11
Requires-Dist: matplotlib (>=3.7.1,<4.0.0)
Requires-Dist: numpy (>=1.24.2,<2.0.0)
Requires-Dist: pandas (>=2.0.1,<3.0.0)
Requires-Dist: pillow (>=10.2.0,<11.0.0)
Requires-Dist: pyarrow (>=14.0.1,<15.0.0)
Requires-Dist: pyyaml (>=6.0,<7.0)
Requires-Dist: scipy (>=1.10.1,<2.0.0)
Requires-Dist: streamlit (>=1.27.0,<2.0.0)
